{
    "Ar36": {
        "error": 0.46821731472539274,
        "error_type": "SEM",
        "filter_outliers_dict": {
            "filter_outliers": true,
            "iterations": 1,
            "std_devs": 2
        },
        "fit": "linear",
        "value": 34.135053045645016
    },
    "Ar37": {
        "error": 2.243111754512014e-07,
        "error_type": "SEM",
        "filter_outliers_dict": {
            "filter_outliers": true,
            "iterations": 1,
            "std_devs": 2
        },
        "fit": "linear",
        "value": 4.448681977063266e-06
    },
    "Ar38": {
        "error": 2.820398150464853e-07,
        "error_type": "SEM",
        "filter_outliers_dict": {
            "filter_outliers": true,
            "iterations": 1,
            "std_devs": 2
        },
        "fit": "linear",
        "value": 7.93180885676733e-07
    },
    "Ar39": {
        "error": 1.516884106913181e-07,
        "error_type": "SEM",
        "filter_outliers_dict": {
            "filter_outliers": true,
            "iterations": 1,
            "std_devs": 2
        },
        "fit": "linear",
        "value": -6.6933089296428654e-06
    },
    "Ar40": {
        "error": 9.586518615866637e-07,
        "error_type": "SEM",
        "filter_outliers_dict": {
            "filter_outliers": true,
            "iterations": 1,
            "std_devs": 2
        },
        "fit": "linear",
        "value": 0.00013343390954369857
    }
}