{
    "AX": {
        "error": 3.234890939676294e-07,
        "error_type": "SEM",
        "filter_outliers_dict": {
            "filter_outliers": false,
            "iterations": 0,
            "std_devs": 0,
            "use_iqr_filtering": false,
            "use_standard_deviation_filtering": false
        },
        "fit": "Average",
        "fn": 10,
        "include_baseline_error": false,
        "n": 10,
        "outlier_excluded": [],
        "reviewed": true,
        "user_excluded": [],
        "value": 9.129839398269723e-07
    },
    "H1": {
        "error": 2.920722711699704e-07,
        "error_type": "SEM",
        "filter_outliers_dict": {
            "filter_outliers": false,
            "iterations": 0,
            "std_devs": 0,
            "use_iqr_filtering": false,
            "use_standard_deviation_filtering": false
        },
        "fit": "Average",
        "fn": 10,
        "include_baseline_error": false,
        "n": 10,
        "outlier_excluded": [],
        "reviewed": true,
        "user_excluded": [],
        "value": -8.379369910471724e-06
    },
    "H2": {
        "error": 5.071695983619625e-07,
        "error_type": "SEM",
        "filter_outliers_dict": {
            "filter_outliers": false,
            "iterations": 0,
            "std_devs": 0,
            "use_iqr_filtering": false,
            "use_standard_deviation_filtering": false
        },
        "fit": "Average",
        "fn": 10,
        "include_baseline_error": false,
        "n": 10,
        "outlier_excluded": [],
        "reviewed": true,
        "user_excluded": [],
        "value": -3.017590982778984e-06
    },
    "L1": {
        "error": 3.2877908666055756e-07,
        "error_type": "SEM",
        "filter_outliers_dict": {
            "filter_outliers": false,
            "iterations": 0,
            "std_devs": 0,
            "use_iqr_filtering": false,
            "use_standard_deviation_filtering": false
        },
        "fit": "Average",
        "fn": 10,
        "include_baseline_error": false,
        "n": 10,
        "outlier_excluded": [],
        "reviewed": true,
        "user_excluded": [],
        "value": -4.2276154772480367e-07
    },
    "L2": {
        "error": 0.04898979528149972,
        "error_type": "SEM",
        "filter_outliers_dict": {
            "filter_outliers": false,
            "iterations": 0,
            "std_devs": 0,
            "use_iqr_filtering": false,
            "use_standard_deviation_filtering": false
        },
        "fit": "Average",
        "fn": 10,
        "include_baseline_error": false,
        "n": 10,
        "outlier_excluded": [],
        "reviewed": true,
        "user_excluded": [],
        "value": 0.2800000049173832
    }
}